telegraph/__init__.py
telegraph/aio.py
telegraph/api.py
telegraph/exceptions.py
telegraph/upload.py
telegraph/utils.py
telegraph-2.1.0.dist-info/LICENSE
telegraph-2.1.0.dist-info/METADATA
telegraph-2.1.0.dist-info/WHEEL
telegraph-2.1.0.dist-info/top_level.txt
telegraph-2.1.0.dist-info/RECORD
