Metadata-Version: 2.1
Name: telegraph
Version: 2.1.0
Summary: Telegraph API wrapper
Home-page: https://github.com/python273/telegraph
Author: python273
Author-email: telegraph@python273.pw
License: MIT
Download-URL: https://github.com/python273/telegraph/archive/v2.1.0.zip
Platform: UNKNOWN
Classifier: License :: OSI Approved :: MIT License
Classifier: Operating System :: OS Independent
Classifier: Programming Language :: Python
Classifier: Programming Language :: Python :: 3
Classifier: Programming Language :: Python :: 3.6
Classifier: Programming Language :: Python :: 3.7
Classifier: Programming Language :: Python :: 3.8
Classifier: Programming Language :: Python :: 3.9
Classifier: Programming Language :: Python :: 3.10
Provides-Extra: aio
License-File: LICENSE
